primer_paquete_jmbv/__init__.py
primer_paquete_jmbv/test.py
primer_paquete_jmbv-0.0.1.dist-info/LICENSE.txt
primer_paquete_jmbv-0.0.1.dist-info/METADATA
primer_paquete_jmbv-0.0.1.dist-info/WHEEL
primer_paquete_jmbv-0.0.1.dist-info/top_level.txt
primer_paquete_jmbv-0.0.1.dist-info/RECORD
