Metadata-Version: 2.1
Name: primer-paquete-jmbv
Version: 0.0.1
Summary: El primer paqquete de Python que he creado
Home-page: https://github.com/juanmabv/primer_paquete
Author: Juan Manuel Batista Velásquez
Author-email: juanmabatistav@gmail.com
License-File: LICENSE.txt
